{
  "admin":{
    "tiles" : ["COLLEGES", "DEPARTMENTS", "PROFESSORS", "SUBJECTS", "SURVEY", "REPORTS", "MANAGE LOGIN", "SETTINGS"],
    "fa_icons" : ["fa-institution", "fa-users", "fa-user", "fa-book", "fa-check-square-o", "fa-line-chart", "fa-lock", "fa-cogs"],
    "bg_style" : ["bg-blue", "bg-red", "bg-yellow", "bg-green", "bg-red", "bg-purple", "bg-red", "bg-dark"],
    "url" : ["../../../admin/manage", "../../../admin/manage", "../../../admin/manage", "../../../admin/manage", "../../../admin/survey", "../../../admin/reports", "../../../admin/manage_login", "../../../admin/settings"]
  },

  "feeder":{
    "tiles" : ["PROFESSORS", "SUBJECTS", "QUESTIONS", "SURVEY", "REPORTS", "SETTINGS"],
    "fa_icons" : ["fa-user", "fa-book", "fa-question", "fa-check-square-o", "fa-line-chart", "fa-cogs"],
    "bg_style" : ["bg-blue", "bg-red", "bg-green-sharp", "bg-yellow", "bg-green", "bg-dark"],
    "url" : ["../../../feed_analyzer/professor", "../../../feed_analyzer/subjects", "../../../feed_analyzer/questions", "../../../feed_analyzer/survey", "../../../feed_analyzer/reports", "../../../feed_analyzer/settings"]
  },

  "principal":{
    "tiles" : ["DEPARTMENT REPORTS", "PROFESSOR REPORTS", "SUBJECT REPORTS", "SETTINGS"],
    "fa_icons" : ["fa-user", "fa-book", "fa-question", "fa-check-square-o"],
    "bg_style" : ["bg-blue", "bg-red", "bg-green-sharp", "bg-yellow"],
    "url" : ["../../../principal/departmentreports", "../../../principal/professorreports", "../../../principal/subjectreports", "../../../principal/settings"]
  },

  "hod":{
    "tiles" : ["UPLOAD DETAILS", "SURVEY STATUS", "DEPARTMENT REPORTS", "PROFESSOR REPORTS", "SUBJECT REPORTS", "SETTINGS"],
    "fa_icons" : ["fa-upload", "fa-check-square-o", "fa-line-chart", "fa-line-chart", "fa-cogs"],
    "bg_style" : ["bg-blue", "bg-red", "bg-green-sharp", "bg-green", "bg-yellow"],
    "url" : ["../../../headofdepartment/upload", "../../../headofdepartment/hodsurvey", "../../../headofdepartment/department", "../../../headofdepartment/professor", "../../../", "../../../headofdepartment/settings"]
  }
}